LICENSE
README.md
setup.py
fib_prusty/__init__.py
fib_prusty/version.py
fib_prusty.egg-info/PKG-INFO
fib_prusty.egg-info/SOURCES.txt
fib_prusty.egg-info/dependency_links.txt
fib_prusty.egg-info/entry_points.txt
fib_prusty.egg-info/top_level.txt
fib_prusty/cmd/__init__.py
fib_prusty/cmd/fib_numb.py
fib_prusty/fib_calcs/__init__.py
fib_prusty/fib_calcs/fib_number.py
fib_prusty/fib_calcs/fib_numbers.py
fib_prusty/tests/__init__.py
fib_prusty/tests/fib_prusty/__init__.py
fib_prusty/tests/fib_prusty/fib_calcs/__init__.py
fib_prusty/tests/fib_prusty/fib_calcs/test_fib_number.py
fib_prusty/tests/fib_prusty/fib_calcs/test_fib_numbers.py